diplomat/__init__.py
diplomat/diplomat.py
diplomat-0.1.2.dist-info/LICENSE
diplomat-0.1.2.dist-info/METADATA
diplomat-0.1.2.dist-info/WHEEL
diplomat-0.1.2.dist-info/top_level.txt
diplomat-0.1.2.dist-info/RECORD
