Metadata-Version: 2.1
Name: diplomat
Version: 0.1.2
Summary: is the arbiter between shell scripts and commands.
Home-page: https://gitlab.com/wobcom/diplomat
Author: Veit Heller
Author-email: veit.heller@port-zero.com
License: GPLv3
Keywords: shell scripting subprocess
Platform: UNKNOWN
Classifier: Development Status :: 3 - Alpha
Classifier: Topic :: Utilities
